reflekt/__init__.py
reflekt/_templates/dbt_package/.gitignore
reflekt/_templates/dbt_package/README.md
reflekt/_templates/dbt_package/dbt_project.yml
reflekt/_templates/dbt_package/models/.gitkeep
reflekt/_templates/reflekt_project/.gitignore
reflekt/_templates/reflekt_project/README.md
reflekt/_templates/reflekt_project/artifacts/.gitkeep
reflekt/_templates/reflekt_project/schemas/.gitkeep
reflekt/_templates/reflekt_project/schemas/.reflekt/meta/1-0.json
reflekt/_validation/profile/1-0.json
reflekt/_validation/project/1-0.json
reflekt/builder/__init__.py
reflekt/builder/_schemas/segment_common/1-0.json
reflekt/builder/dbt.py
reflekt/builder/handler.py
reflekt/casing.py
reflekt/cli.py
reflekt/constants.py
reflekt/dumper.py
reflekt/errors.py
reflekt/flatson.py
reflekt/linter.py
reflekt/profile.py
reflekt/project.py
reflekt/registry/__init__.py
reflekt/registry/avo.py
reflekt/registry/handler.py
reflekt/registry/segment.py
reflekt/reporter/jsonschema2md.py
reflekt/reporter/reporter.py
reflekt/tracking.py
reflekt/warehouse.py
reflekt-0.6.0.dist-info/LICENSE
reflekt-0.6.0.dist-info/LICENSES/Apache-2.0.txt
reflekt-0.6.0.dist-info/LICENSES/BSD-3-Clause.txt
reflekt-0.6.0.dist-info/METADATA
reflekt-0.6.0.dist-info/WHEEL
reflekt-0.6.0.dist-info/entry_points.txt
reflekt-0.6.0.dist-info/RECORD
