Metadata-Version: 2.1
Name: reflekt
Version: 0.6.0
Summary: A CLI tool to define event schemas, lint them to enforce conventions, publish to a schema registry, and build corresponding data artifacts (e.g., dbt sources/models/docs).
Home-page: https://github.com/GClunies/Reflekt
License: Apache-2.0
Keywords: events,jsonschema,analytics,business-intelligence,data-modeling,dbt,snowflake,redshift,segment,avo
Author: Gregory Clunies
Author-email: greg@reflekt-ci.com
Requires-Python: >=3.9,<3.12
Classifier: License :: OSI Approved :: Apache Software License
Classifier: Programming Language :: Python :: 3
Classifier: Programming Language :: Python :: 3.9
Classifier: Programming Language :: Python :: 3.10
Classifier: Programming Language :: Python :: 3.11
Requires-Dist: gitpython (>=3.1.42,<4.0.0)
Requires-Dist: google-cloud-bigquery-storage (>=2.24.0,<3.0.0)
Requires-Dist: inflection (>=0.5.1,<0.6.0)
Requires-Dist: jsonschema (>=4.21.1,<5.0.0)
Requires-Dist: loguru (>=0.7.2,<0.8.0)
Requires-Dist: python-dotenv (>=1.0.1,<2.0.0)
Requires-Dist: pyyaml (>=6.0.1,<7.0.0)
Requires-Dist: redshift-connector (>=2.0.918,<3.0.0)
Requires-Dist: rich (>=13.7.0,<14.0.0)
Requires-Dist: segment-analytics-python (>=2.3.2,<3.0.0)
Requires-Dist: snowflake-sqlalchemy (>=1.5.1,<2.0.0)
Requires-Dist: sqlalchemy-bigquery (>=1.9.0,<2.0.0)
Requires-Dist: sqlalchemy-redshift (>=0.8.14,<0.9.0)
Requires-Dist: typer (>=0.9.0,<0.10.0)
Project-URL: Repository, https://github.com/GClunies/Reflekt
